{
  "collapse-filter": false,
  "search": "",
  "showTags": true,
  "showAttachments": false,
  "hideUnresolved": false,
  "showOrphans": false,
  "collapse-color-groups": false,
  "colorGroups": [],
  "collapse-display": false,
  "showArrow": true,
  "textFadeMultiplier": -2.1,
  "nodeSizeMultiplier": 1,
  "lineSizeMultiplier": 1,
  "collapse-forces": false,
  "centerStrength": 0.473958333333333,
  "repelStrength": 17.6041666666667,
  "linkStrength": 0.8125,
  "linkDistance": 312,
  "scale": 0.5522499710648205,
  "close": false
}